odoo/addons/crm_stage_probability/README.rst
odoo/addons/crm_stage_probability/__init__.py
odoo/addons/crm_stage_probability/__manifest__.py
odoo/addons/crm_stage_probability/data/crm_stage.xml
odoo/addons/crm_stage_probability/i18n/crm_stage_probability.pot
odoo/addons/crm_stage_probability/i18n/it.po
odoo/addons/crm_stage_probability/models/__init__.py
odoo/addons/crm_stage_probability/models/crm_lead.py
odoo/addons/crm_stage_probability/models/crm_stage.py
odoo/addons/crm_stage_probability/readme/CONFIGURE.rst
odoo/addons/crm_stage_probability/readme/CONTRIBUTORS.rst
odoo/addons/crm_stage_probability/readme/DESCRIPTION.rst
odoo/addons/crm_stage_probability/static/description/icon.png
odoo/addons/crm_stage_probability/static/description/index.html
odoo/addons/crm_stage_probability/tests/__init__.py
odoo/addons/crm_stage_probability/tests/test_crm_lead_probability.py
odoo/addons/crm_stage_probability/views/crm_lead.xml
odoo/addons/crm_stage_probability/views/crm_stage.xml
odoo/addons/crm_stage_probability/wizard/__init__.py
odoo/addons/crm_stage_probability/wizard/crm_lead_stage_probability_update.py
odoo/addons/crm_stage_probability/wizard/crm_lead_stage_probability_update.xml
odoo13_addon_crm_stage_probability-13.0.1.0.1.dev8.dist-info/METADATA
odoo13_addon_crm_stage_probability-13.0.1.0.1.dev8.dist-info/WHEEL
odoo13_addon_crm_stage_probability-13.0.1.0.1.dev8.dist-info/top_level.txt
odoo13_addon_crm_stage_probability-13.0.1.0.1.dev8.dist-info/RECORD
