Metadata-Version: 2.1
Name: odoo13-addon-crm-stage-probability
Version: 13.0.1.0.1.dev8
Summary: Define fixed probability on the stages
Home-page: https://github.com/OCA/crm
Author: Camptocamp, Odoo Community Association (OCA), Odoo SA
Author-email: support@odoo-community.org
License: AGPL-3
Platform: UNKNOWN
Classifier: Programming Language :: Python
Classifier: Framework :: Odoo
Classifier: Framework :: Odoo :: 13.0
Classifier: License :: OSI Approved :: GNU Affero General Public License v3
Classifier: Development Status :: 3 - Alpha
Requires-Python: >=3.5
Requires-Dist: odoo <13.1dev,>=13.0a
